{"version": "1", "message": "ERROR: Hidden Testcases server unreachable.", "problem_id": "ads2_m13_a1_1", "user_id": "Sahith-8055", "score": {"sample": {"0": {"execution_time": 0.26260995864868164, "passed": true}, "1": {"execution_time": 0.2778000831604004, "passed": true}, "2": {"execution_time": 0.24517464637756348, "passed": true}, "3": {"execution_time": 0.26152586936950684, "passed": true}, "4": {"execution_time": 0.24793314933776855, "passed": true}, "5": {"execution_time": 0.261319637298584, "passed": true}, "6": {"execution_time": 0.2614121437072754, "passed": true}, "7": {"execution_time": 0.27520012855529785, "passed": true}}}, "check_style_score": "1/1"}