{"version": "1", "message": "ERROR: Hidden Testcases server unreachable.", "problem_id": "ads2_m13_a1_1", "user_id": "Sahith-8055", "score": {"sample": {"0": {"execution_time": 0.3132905960083008, "passed": true}, "1": {"execution_time": 0.27881574630737305, "passed": true}, "2": {"execution_time": 0.25740575790405273, "passed": true}, "3": {"execution_time": 0.3076291084289551, "passed": true}, "4": {"execution_time": 0.4166138172149658, "passed": true}, "5": {"execution_time": 0.406200647354126, "passed": true}, "6": {"execution_time": 0.2998218536376953, "passed": true}, "7": {"execution_time": 0.27083349227905273, "passed": true}}}, "check_style_score": "0/1"}